datashift/__init__.py
datashift/datapipeline.py
datashift/dataset.py
datashift/task.py
datashift-0.1.0.dist-info/METADATA
datashift-0.1.0.dist-info/WHEEL
datashift-0.1.0.dist-info/top_level.txt
datashift-0.1.0.dist-info/RECORD
